autocompletion/__init__.py
autocompletion/_version.py
autocompletion-0.1.1.data/data/share/jupyter/labextensions/autocompletion/build_log.json
autocompletion-0.1.1.data/data/share/jupyter/labextensions/autocompletion/package.json
autocompletion-0.1.1.data/data/share/jupyter/labextensions/autocompletion/static/lib_index_js.7154c6c8501805143ca7.js
autocompletion-0.1.1.data/data/share/jupyter/labextensions/autocompletion/static/lib_index_js.7154c6c8501805143ca7.js.map
autocompletion-0.1.1.data/data/share/jupyter/labextensions/autocompletion/static/remoteEntry.c0a300a13de220ce2f75.js
autocompletion-0.1.1.data/data/share/jupyter/labextensions/autocompletion/static/remoteEntry.c0a300a13de220ce2f75.js.map
autocompletion-0.1.1.data/data/share/jupyter/labextensions/autocompletion/static/style.js
autocompletion-0.1.1.data/data/share/jupyter/labextensions/autocompletion/static/style_index_js.d097b78163772c78dcf1.js
autocompletion-0.1.1.data/data/share/jupyter/labextensions/autocompletion/static/style_index_js.d097b78163772c78dcf1.js.map
autocompletion-0.1.1.data/data/share/jupyter/labextensions/autocompletion/static/vendors-node_modules_css-loader_dist_runtime_api_js-node_modules_css-loader_dist_runtime_cssW-72eba1.1451419f3d39752e951d.js
autocompletion-0.1.1.data/data/share/jupyter/labextensions/autocompletion/static/vendors-node_modules_css-loader_dist_runtime_api_js-node_modules_css-loader_dist_runtime_cssW-72eba1.1451419f3d39752e951d.js.map
autocompletion-0.1.1.data/data/share/jupyter/labextensions/autocompletion/install.json
autocompletion-0.1.1.dist-info/METADATA
autocompletion-0.1.1.dist-info/WHEEL
autocompletion-0.1.1.dist-info/licenses/LICENSE
autocompletion-0.1.1.dist-info/RECORD
